{"m_szDocID":"585990","m_szDocTitle":"ZA8 Zinc-Aluminum Alloy","m_szYear":"2016","m_szDocSumamry":"Home Home Articles News Directory Equipment Software Market Reports Experts Books Journals Blogs Podcasts Videos Events Courses News 3D Printing Adhesives and Sealants Aerospace Materials Aluminum / Aluminium Automotive Materials Biomaterials Building and Construction Business Ceramic Materials Chemistry Clean Technology Coatings and Thin Films Composites Control Systems Corrosion Crystallography Design and Innovation Electronics Energy Events Ferrous Alloys and Metals Fibers Fuel Cell Graphene Iron and Steel Materials Analysis Materials Processing Materials Research Materials Science Material","m_szDocBody":"home home article new directory equipment software market report expert book journal blog podcast videos event course new printing adhesive sealant aerospace material aluminium aluminium automotive material biomaterial building construction business ceramic material chemistry clean technology coating thin film composite control system corrosion crystallography design innovation electronic energy event ferrous alloy metal fibre fuel cell graphene iron steel material analysis material processing material research material science material testing mineral mining modelling simulation nanomaterial nanotechnology product nonferrous alloy metal packaging petrochemical photonic photovoltaic pittcon plastic polymer precious metal rubber elastomer semiconductor sustainable technology titanium tribology article latest article thought leader insight industry azojomo material material supplier application industry metal store equipment chemical analysis atomic absorption spectrometer aas atomic optical emission spectrometer oes benchtop nmr spectrometer electrochemical analysis electron paramagnetic resonance epr spectrometer elemental analyzer ftir accessory ftir spectrophotometer ftnir fourier transform spectrometer fuel lubricant testing gas analyzer gas chromatography gel permeation chromatography handheld raman analyzer handheld xrf analyzer ion chromatography laboratory reactor liquid chromatography mass spectrometer nmr spectroscopy analyzer pharmaceutical analysis equipment raman spectrometer secondary ion mass spectrometry sim spectrometer spectroscopy accessory titrator vapour pressure measurement xray gamma ray detector xray diffractometer xray fluorescence analyzer xray optic xray photoelectron spectroscopy xps xrf spectrometer coating deposition atomic layer deposition system thermal evaporation equipment thin film deposition system coating testing adhesion tester coating thickness gauge coating film deposition consumable eddy current tester ellipsometer glossmeter thin film characterization system electrical property electrical property characterization equipment hall effect measurement system scanning kelvin probe seebeck coefficient measurement system vibrating sample magnetometer vsm zeta potential analyzer equipment testing calibration battery testing solar cell testing fixing fastener bonding fastener flow controller metre field flow fractionation equipment heat treatment ageing oven industrial furnace oven laboratory furnace kiln vacuum furnace laboratory process equipment controlled atmosphere processing environment cryogenic evaporator concentrator laboratory gas generator laboratory heating cooling apparatus laboratory testing sample preparation equipment laboratory water purification system mixer shaker pcb smt handling workstation scientific illumination light source vacuum pump material processing manufacturing printing equipment material accessory boring machine mill particle size reduction plastic processing equipment ultrasonic welding equipment mechanical testing automatic material testing machine biomaterial testing equipment brittleness tester civil engineering material testing equipment cutter grinder polisher drop weight testing machine durometer fatigue testing machine force gauge gauge hardness testing machine impact testing machine material characterization equipment pipe burst hydrostatic tester plastic rubber testing equipment portable hardness tester scratch tester tensile testing machine torque gauge gauge tribometer friction wear tester universal material testing machine microscope acoustic microscope afm raman system atom probe atomic force microscope afm electron beam source fibre analyzer ion beam microscope metallurgical microscope microscopy accessory consumable optical microscope polarising microscope raman microscope raman software sample preparation equipment scanning electrochemical microscope secm scanning electron microscope sem scanning probe microscope scanning transmission electron microscope stem sem raman system stereo microscope transmission electron microscope tem nondestructive testing ndt coating thickness gauge handheld xrf analyzer laser micrometre measurement nondestructive testing ndt equipment portable hardness tester scientific cameras sheet board counter ultrasonic flaw detector xray scattering system saxs waxs optical inspection acoustic microscope borescope ccd cameras colorimeter electron multiplying charge coupled device emccd ellipsometer monochromator optical comparator optical noncontact profiler measurement polarimeter polariscope refractometer scientific cameras oven furnace kiln ageing oven industrial furnace oven laboratory furnace kiln physical property testing adhesion tester analytical test sieve borescope chemisorption analyzer civil engineering material testing equipment density metre diffusivity tester dynamic vapour sorption dvs electron backscatter diffraction ebsd environmental test chamber extensometer extruded profile measurement system ferrography flexometer goodrich flexometer fogging tester gas adsorption analyzer gas pycnometer gas solubility analyzer glossmeter laser micrometre measurement light scattering instrument melt flow index tester metal testing equipment moisture analyzer optical noncontact profiler measurement particle counter particle size analyzer permeameter pharmaceutical analysis equipment plasma processing equipment pore size analyzer profilometer pycnometer rheometer metrology tool sheet board counter shock vibration test system spectrophotometer surface area analyzer surface energy gas chromatograph thickness gauge gauge vapour sorption analyzer viscometer wafer mapping system water sorption analyzer zeta potential analyzer plasma processing plasma diagnostic tool plasma processing equipment process control extruded profile measurement system flow controller metre lubricant condition monitor process control system radiation detector testing geiger counter liquid scintillation counter multichannel analyzer proportional counter radio chemistry sensor detector data logger control system controller data logger gas detector level sensor moisture sensor temperature sensor thermocouple thermal analysis calorimeter differential scanning calorimeter dsc dilatometer flash analysis lfa melting point metre peltier thermostat temperature measurement equipment temperature retraction tester thermal analysis equipment thermal conductivity system thermomechanical analyzer tma product software market report book alloy aluminium asm handbook biomaterial ceramic chemical engineering chemistry clean technology coating composite condensed matter conference proceeding copper corrosion design elastomer electronic engineering fluid fuel cell glass glaze heat treatment instrumentation iron magnetism material processing material science material testing measurement science mechanic mem metallurgy metal microscopy nanotechnology optic photonic cell physic plastic polymer semiconductor soft matter spectroscopy steel thermodynamic thermoplastic titanium welding journal biomaterial ceramic material chemistry coating thin film composite corrosion crystallography energy material processing material science metal alloy mineral nanotechnology polymer solgel videos adhesive bonding axaa conference biomaterial carbon fibre future direction interview ceramic material coating composite material corrosion emc manchester ferrous alloy functional material gas chromatography graphene hard material temperature material iconn interview light alloy m&m phoenix arizona usa machining mass spectrometry material austceram material processing material science technology mst material science technology mst material testing characterisation metal casting foundry mrs fall meeting video interview mrs fall meeting mrs fall meeting mrs fall meeting video interview nanomaterial nonferrous alloy pittcon interview pittcon interview pittcon interview pittcon pittcon precious metal recycled sustainable material rubber elastomer spectrometer stainless steel structural material thermoplastic thermosetting polymer welding brazing course course event contact meet team term advertise browse bymaterialsapplicationsindustry advertise term sponsor trending material storey material electric car battery researcher develop metallic material transform steel industry carbon material loofah sponge improve lithium battery fei enhance dualbeam productivity precision easeofuse slice software fraunhofer stratasy redefine movie industry advanced printing solution improving lcm separation onsite nitrogen generation sponsor insight industry proving roi scanning technology industrial quality assurance application interview martin schuster improving lcm separation onsite nitrogen generation increased uptime fast response preventive maintenance serviceguard struer interview lar kaln latest material article proving roi scanning technology industrial quality assurance application interview martin schuster comparison thermal fluid steam detection removal prevention water thermal oil system comparing particle rheology smoothy made blender power law model evaluate product spreading characteristic rotational rheometer request quote zincaluminum alloy written azom topic covered introduction chemical composition physical property mechanical property designation application introduction zinc aluminium alloy alloy zinc base metal higher concentration aluminium traditional zinc alloy metal alloy magnesium copper concentration aluminium alloy represented number alloy mean aluminium percentage zinc aluminium alloy performance alloy exhibit good strength hardness show good wear resistant property compared zinc aluminium alloy common zincaluminum alloy class zinc aluminium alloy zamak alloy alloy die cast alloy short freezing excellent fluidity die casting suitable thin wall component due good hardness strength pressure tightness datasheet elaborate chemical composition property alloy chemical composition chemical composition zincaluminum alloy table element zinczn remainder aluminumal copper iron magnesium lead cadmium tin physical property table discusse physical property zincaluminum alloy property metric imperial density mechanical property mechanical property zincaluminum alloy tabulated below property metric imperial tensile strength mpa ksi yield strength mpa ksi modulus elasticity gpa ksi poisson ratio designation designation denote zincaluminum alloy below aca application zincaluminum alloy application bearing die casting thin wall decoration date added updated comment review update add article cancel reply comment leave feedback logout public comment private feedback azomcom submit home new article directory equipment software market report expert book journal blog podcast videos event course azomcom azonetwork owned operated azomcom limited copyright azomcom information service accordance term condition cooky continuing browse agreeing cooky here","m_szGeo1":"United Kingdom","m_szSourceType":"source_general","m_szSrcUrl":"http://www.azom.com/article.aspx?ArticleID=9288","m_Places":["Kilns","Boring","Surface Area","Manchester","Uk","United States","Made","Tin"],"m_People":["Nir Fourier","Sem Raman","Eddy Current","Diffusivity Tester","C. Martin Schuster","Lars Kaln√¶s"],"m_Companies":["Plastics","Sec","Shakers","Particle","Plastic","Force Gages","Torque","Gages","Universal","Atom","Goodrich","Asm","Emc","M&m","Phoenix, Arizona","Slice","Stratasys"],"m_BiGrams":["material testing","testing machine","zincaluminum alloy","material processing","material science","testing equipment","aluminium alloy","thin film","processing material","measurement system","physical property","chemical composition","zinc aluminium","software market","market report","ceramic material","control system","alloy metal","analysis equipment","thickness gauge","furnace kiln","processing equipment","electron microscope","plasma processing","pittcon interview","interview pittcon","mechanical property"],"m_TriGrams":["zinc aluminium alloy","software market report"],"m_SocialTags":[],"m_Topics":[],"m_Industry":[],"m_Technology":[],"m_BiCnt":[7,7,7,5,5,5,5,4,4,4,4,4,4,3,3,3,3,3,3,3,3,3,3,3,3,3,3],"m_TriCnt":[4,3],"m_iDocBodyWordCnt":1292}
