{"m_szDocID":"626458","m_szDocTitle":"Powering cities of the future - The Science Show - ABC Radio National (Australian Broadcasting Corporation)","m_szYear":"2016","m_szDocSumamry":"Powering cities of the future Image: (Getty Images) In just over 35 years, the world population is expected to increase by almost 50%, from 7 billion people now to 10 billion. Without change, in less than 20 years enough fossil fuel will have been burnt to increase average global temperature by an average of 2 degrees Celsius. Some areas in the Arctic are already 5 degrees Fahrenheit above average. Urgent action is required. Coal and oil needs to stay in the ground and other sources of power need to be implemented quickly. But such a transition will not happen overnight. So what are the option","m_szDocBody":"powering city future image getty image year world population expected increase billion people billion change year fossil fuel burnt increase average global temperature average degree celsius areas arctic degree fahrenheit average urgent action required coal oil stay ground source power implemented quickly transition happen overnight option sydney australian city france nuclear powered china smog managed embrace solar power quickly geological australia assembled forum scientist engineer discuss option australia reflect achievement elsewhere these transcript robyn william powering australian city challenge year science show choice game changed option heard before form desert tech initiative put solar sahara michael blastland bbc world service michael blastland common solar panel photovoltaic cell turning sunlight directly electricity storage mean battery capture heat store liquefied salt heat create steam turn turbine anthony patt mean produce power middle night nice sahara desert big cloudy weather localised thermal storage provide absolutely reliable power michael blastland problem then fact sun down anthony patt nice concentrated solar power generate clock store heat heat hour drive turbine generate electricity then michael blastland objection two power line africa europe leak energy sieve anthony patt know united state boston area boston huge amount electricity northern qubec mile single power cable hard build long political approval jurisdiction through michael blastland lose power anthony patt lose power mile lose power michael blastland biggest technological objection think overcome anthony patt technology huge objection michael blastland objection glass cleaned scarce water say air job too well enough robyn william tony patt swiss institute technology bbc world service follow idea future programme perhap forum way including desert power city after forum put geological australia university south wale speaker tony irwin technical director snr nuclear technology year experience nuclear reactor chairman engineer australia nuclear engineering panel visiting lecturer master nuclear science anu canberra tony irwin tony irwin robyn well australia lucky country fabulous reserve fossil fuel cheap electricity year sudden start emission unit electricity generated pretty awkward position coal black coal brown coal well end emission hold real world record estonia oecd emission hold world record outright world record swimming hazelwood power station biggest emitter world emitting tonne minute fantastic stuff end australia emission china come china nuclear lot wind less imagine france this bottom bottom half emission lot country putting limit emission plant megawatt hour country usa canada put limit emission mean ccs coal work gas turbine combined cycle bit longer time australian situation market operator produce day emission state expected victoria brown coal high south wale black coal queensland black coal south australia bit surprise megawatt wind expected low problem back wind something backed coal gas contrast tasmania tasmania wind backed hydro typically level wind variable system back back give outcome moment nem carbon tax off incentive burn brown coal emission moment something you robyn william speaker professor mary okane south wale chief scientist engineer directed south wale government conduct comprehensive review coal seam gas related activity focusing human health environmental impact chief scientist please mary okane great period low productivity growth energy innovation board fossil uranium thorium renewable source mixe lot interesting storage anywhere australia part australian economy form energy economy energy technology exciting export thing martin thomas sitting there great energy figure australia remember incredibly good international symposium put together martin melbourne academy tech science engineering group world spoke pointed energy australia had remember wonderful picture japanese put japanese put year future great big line australia japan pointed australia exporting electricity japan year time robyn william much building speaker lot building building puzzle our abc ultimo people sit shiver freezing cold summer temperature adjusted suit big bloke blue suit women wear clothes should exciting spend money energy building cool want phone building bloke downstair say can make warmer turning air conditioning difficulty well professor deo prasad director university south wale centre sustainable built environment international authority sustainable building city leading advocate sustainability australia building please speak first deo prasad you research centre building major programme push performance low carbon world technology product material low embedded carbon material tool data design planning innovation drive performance building scale carbon net energy beyond building net producer energy back system opposed drawing that australian industry benefit technology research building product manufacturer technology manufacturer material future compete globally pressure part world technology market ready compete globally sense city programme upscale building put lot building city issue transport energy range between tree offset mitigate extreme temperature beginning more extent work involve policy city sydney example save energy extensive canopy greening tree form canopy reduce temperature cooling load higher example policy advise them programme community extent people engaged star house putting twostar person two threestar outcome star house performing eight star level type energy efficiency talking about demandside efficiency mentioned very important absolutely reduce demand energy make people comfortable time lowest energy use extent generate energy run city city familiar trigen rollout plan city those study term engineering governance business model eventually drive change storage house generate electricity use happen time day generate day peak demand evening align energy storage important hear tesla big new lot option technology forever changing and mentioned empowering people pathway good policy good education very important view you robyn william much jack singh trobe university device three year old left device denmark house melbourne garage fridge left switched off denmark game kid device well cheap show save amount dollar week extra pocket money good play game turning off professor ben hankamer university queensland founding director solar biofuel consortium developing highefficiency micro algal biofuel production system ben hankamer briefly moving billion people food water fuel achieve reduce emission challenge face global energy model fast energy fuel have interesting global energy modelling fuel stay twodegree climate change limit basically year make complete transition neutral challenge solution renewable energy source big global impact lot development solar technology example electricity heard electricity global energy demand form fuel fuel solution work develop renewable fuel solution algae basically cell factory carbon dioxide water nutrient make range product ultimately scale nonarable land vision food versus fuel issue range system people developing internationally integrated city city provide need job identify optimise further system integration integrate strain algae production system harvesting system separate sublime ridiculous optimise profitability energy balance algae range product pharmaceutical product fuel important drive cost curve algae biomedicine centre developing example algae production vaccine dengue virus solar biofuel consortium build make range fuel solution develop harvesting system crude oil biocrude oil generate hydrogen algae driving car much robyn william finally newcastle gary ellem tom farrell institute university newcastle recent work focused modelling scale economic alternative energy sequestration land management system development innovative biomass technology micro algae gary ellem show lovely picture start with wrong conference showed picture transport bit weird map map sydney place metre public transport bad side map public transport public transport minute turn consequence turn people there fairly directly wait minute public transport public transport directly choice called private passenger car fact choice make transport trip personal mode private passenger car depending city rest walking public transport turn feet wonderful thing there consequence consequence energy energy energy done south wale people obsess talk energy talk electricity term gas gas imported lot local gas south wale coal bed south wale gas coal bed methane camden rest pipeline moomba south australia victoria piping gas oil sliver renewable basically chip fat oil turned renewable lard cow rest imported southeast asia singapore import oil send smokestack car turn import thing import oil vehicle run private passenger vehicle energy infrastructure import thing roll car couple year rich year rich end add annual cost import good import state drive private passenger transport system cost billion year import scale coal export sector largest export technically moment selling coal money buy oil car use turn coal sector okay excited alternative energy technology alternative energy technology solar panel pretty year exciting transport game well train bicycle same car pretty new electric car well turn electric car petrol car pretty exciting technology flying technology digital sphere smash technology digital sphere transport interesting electric autonomous car designed shared mean designed pull phone pick mean car anymore car time car sitting garage worse still sitting street taking public space this oneth number vehicle job term transport cut import vehicle factor obvious electric cheapest effective run car technology screaming car exist smart bring sort technology make test bed cost billion year robyn william gary ellem university newcastle listening forum powering city question audience increase installation solar power renewable electricity source apartment building rental property that audience member well small roof space compared number people living apartment building part question rental property incentive landlord put expensive renewable energy source deo prasad project kogarah medium rise development apartment storey gave proposal cover roof photovoltaic earning offset body corporate cost cover common area lighting common area energy need company giving half cent concession kilowatt power electricity cost occupant winwin netherland lot policy utility required meet target green energy generation roof substructure put roof generate offset advantage community coming back question small apartment limit there facade type application orientation like tradeoff efficiency term comparison appropriately inclined facing true north versus vertical facing north well tradeoff generate electricity facade robyn william jerusalem building solar law gary ellem china building storey solar hot water interesting big tower block withbut again hot water person long shower all discussing interesting point basically surface area versus local energy use factory large roof space suburban house good roof space comparison size easier interesting solar power suburb kind black hole sustainability bigger house higher energy use live drive further term renewable energy renewable energy sun distributed exposed surface area chance suburb way home sustainability opposed black hole sustainability kind interesting asked question focused rental accommodation economic solar hard about well rental person money back real estate south wale recent study found people prepared pay week rental home solar back additional rental point put solar roof increased capital building fact study increase building dollar watt installed solar interesting cost dollar watt put solar there fact put solar rental property increase rental propertybecause solar there instantly pay payback time increased capital cost building sell time extra week rental make economic sense give argument person own house robyn william tony manning say speaking science educator interesting discussion pluse minuse current versus alternative energy source give send place correct unarguable rundown cost megawatt hour energy source subsidy guise and corollary price heading mary mary okane iea international energy agency good work cost bringing date australia study john burgess academy technological science engineering looked cost looked cost heading happened great study website academy tech science engineering grattan institute fantastic work regard tony wood lot work easy find robyn william understand confusion people mark diesendorffrom university south wale sufficient difference technology give baseline energy mary okane john burgess projection thing ben hankamer calculation recently putting solar panel roof put solar panel roof year ago lot expensive now system paying order sort argument hear new renewable expensive based capital cost buying thing work year lifespan solar panel producing electricity kilowattsso generally queensland based kilowatt panel kilowatt hour day roughly speaking system kwh day basis year cost cent kwh electricity think robyn bill high continue high higher energy supplier charge customer percentage asset transmission grid transmission people solar solar cheaper people cost asset divided trend solar now trend existing infrastructure cost audience member sharon gary ellem shared car idea problem sociopolitical looked social side australian giving car emotional attachment them gary ellem propose people people thinkthey back say are car thought taking car give car nicer have voluntarily fun cost effective strange people way strange car sold year idea freedom freedom wrapped car people age younger freedom this compatible steering wheel robyn william showing audience mobile phone gary ellem turn fact younger people buy car car capital cost force park pain butt car car pain horrible legacy love home house exciting happen today youth force this forced situation case people this service available people say well car car anymore this reliable enough car car weekend audience member admire confidence that gary ellem making sureas technology fear people technology context autonomous mean terminator you japanese perspective autonomous mean robot big eye friend cultural aspect important thing yes japan put robot big eye friend looked design car koala teddy bear reason that supposed scary robyn william private car year make unmanly unaustralian audience member renewable energy car process changing people mindset australian love car gary ellem but think love horse well people love horse bulk transport anymore audience member time period essential reducing footprint audience member mike question tony irwin low emitting nuclear option plan storage management neutralisation radioactive waste product recall research strategy deal longlived actinide essentially consuming fuel wondered research ongoing productive solution manage nuclear waste tony irwin actinide longlived stuff spent fuel longlived thousand thousand year neat solution trialled ebrii reactor fast neutron reactor put fuel reactor fast neutron reactor actinide fission transform fission product shortlived easy manage scheme demonstrated successfully project stopped clinton administration relooked now neatest solution longlived waste spent fuel solution geological repository common one stage licenced finland sweden metre deep rock canister surround bentonite clay survive hundred thousand year that burning actinide solution audience member tony wheeler declaration interest plastic professor university south wale work area close deo user virtue design faculty design people question turn head designer accommodate user generation electricity fuel affordable sustainable socially progressive architecture make energy free amount kilowatt hour free socially disadvantaged people social housing buy solar panel provided state that simply make free level step step step again time big house point piper light night paying loy power station idea lifestyle car transport necessarily buy electricity heating comfortable house turn head disruptive technology distributing people localised solar power battery wealthy solution concern make equitable solution society way address user solution ben hankamer subsidise moment australia billion subsidy fossil fuel davos leftwing tank taxing subsidising big debate queensland fact electricity price people left grid pay panel work billion subsidy give fossil fuel made subsidising solar panel household start taking price panel price bottom example bringing realm colour price continue drop kind thinking there robyn william ben subsidy broke ben hankamer well good question subsidy internationally billion lot lot lobbying imagine subsidising fuel price down locking type fuel moment diesel excise mining industry mean people diesel make difficult fuel renewable fuel market fight fuel infrastructure subsidy robyn william mary answer that mary okane yes couple comment that sort clever economic model district heating cooling energy issue example suburb vienna geothermal heating considerable interest suburb sydney similar innovative firm running yass geothermal heating cooling put apprentice local areas energy producing socialise energy use heating cooling managed district level solar production battery leichardt council energy producer bit opened telcos aarnet connected university remember aarnet telco australian academic research network telco telecommunication university csiro similarly group energy company wanted add something robyn previous answer storage nuclear waste remind people great australian invention won australia prize synroc synroc forgotten mention thing great believer australia geothermal capacity enormous talking eminent chemist melbourne pointed great drilling kilometresor five generally five deep geothermal source drop waste down geothermal nuclear uranium thorium waste contributing geothermal deo prasad people perception satisfaction productivity workplace beginning indoor environment greener low carbon building lead satisfaction people productive making difference productivity workplace office evident building city moment study determine order improvement measured productivity mean people design greener building based social related data economic benefit result higher productivity audience member bureau statistic report energy industry household consumer focusing industry discussion industry gary ellem sound good way reality baseload electricity south wale sucked place aluminium smelter drop productivity electricity understand aluminium sector bit industry suck enormous amount power produce good billiondollar export sector lot room move starting interesting stuff aluminium term power effectively working residential sector freak plus degree day crank airconditioner scary grid aluminium smelter say wait minute moment buying electricity megawatt hour current price megawatt hour turn pot hour sell enormous electricity load back grid way buffer residential system residential system kind spike spike industry slack say problem big energy user industry spent lot time thinking this incidental stuff there office building use energy small fraction revenue company tend ignore major part revenue spend enormous amount effort maximise low hanging fruit industry big energy user smaller energy user revenue sort thinking deal residential sector ben hankamer yes fuel aspect address industry way airline industry difficult electric industry part seriously fuel part mix say audience member question irwin term advance technology and point safety smallscale nuclear power plant talking megawatt range potential uptake residential sector appetite potentially small scale fit distributed supply network well tony irwin big potential small watt reactor generally defined megawatt electrical typically megawatt electrical real advantage small easy make safe rely external cooling fukushima gravity natural circulation relying passive system put reactor underground good hazard unauthorised interference build factory bring instal plug play reduce construction time capital cost big nuclear power plant big initial upfront cost smaller small modular reactor add them demand add australia good step nuclear smaller type reactor gary ellem rest world not ridiculously blessed fossil fuel oil enormous amount coal enormous amount gas ridiculously blessed renewable astounding solar resource wind resource southern australia ridiculous massive geothermal resource resource renewable cheapest one hydro australia thinking nuclear option choice choice base social economic issue choice nuclear necessarily northern european country northern hassle big difference population square metre energy hectare land higher renewable distributed necessarily deliver them bigger difference summer winter solar fall horribly winter bigger energy use heating cook choice renewable simply produce renewable energy power grid extraordinary energy efficiency country world strategic position energy australia blessed position kind interesting way trouble thinking issue excess riches opposed deficit joy distributed solar rooftop engage financial system homeowner scale production system centralised solar distributed production system aye sun build panel large factory china because point understand renewable energy policy manufacturing policy connect two consumer people product producer australia say point time feedin tariff understand connect manufacturing policy question china country sunif solar radius map world dark smog cloud top china country sun world largest coal producer factor four world largest solar panel producer answer simple understand manufacturing problem manufacturing policy policy buy world solar manufacturing industry build solar panel china give land free give nointerest loan make building radius publicly owned put solar panel roof year sale guaranteed put import tariff competing productwhat want robyn william answer gary ellem know cost production term cost labour withthey understand largescale manufacturing policy connect moment yes manufacturing centralised china bring scale bringing mum dad investorsthink huge crowd funding plan solar scaled bringing mum dad investor twos industry back manufacturing industry import industry deo prasad project this example connecting together putting solar panel china lot intellectual property australia manufactured china project exploring building material steel substrate manufactured australia forming steel stage cladding roof wereinstead putting colour bond put solar encapsulated extra cost cost silicon cost coming time manufacture product australia setup there adding bit more example glazing glass australia trade efficiency cover building result lot advantage residential level talked mismatch generating needing household industrial demand commercial demand largely day match good term generating demand offsetting demand time building cladding material opposed putting added panel top doubling solar rain produce energy product capture electrical output thermal output large part solar fall roof lot waste heat there capture service inside building heat example put desiccant cooling system heat cool inside building product opportunity areas future martin thomas you martin thomas name place question mention case otherwise favoured renewable energy fact ran renewable energy crc year ago deo prasad significant contributor privileged work ziggy switkowski uranium task force year ago question this panel australia decide adopt nuclear energy part low emission low carbon strategy depend outcome south australian royal commission nuclear fuel cycle occurring moment panel objective put forward eloquently and share say objective include low carbon low emission safe reliable affordable and last contributed effectively progressively replacing australias ageing coalfired power station the time ready come modern socalled generation iii inherently safe nuclear power reactor existing grid pay for reactor incorporate amount design world moment suggest looked westinghouse reactor looked seriously ben hankamer technology achieve thing profitable positive energy balance low greenhouse gas emission nuclear contribute space important life cycle analysis include cost involved storage well happened past people said know nuclear cheapest thing cost storing long period time included cost level playing field thing done point make life risky risky faced fact modelling done burn carbon burn stay twodegree climate change limit year complex mix achieve option gary ellem enjoyed ziggy report part that favourite graph read properly overcomplicated carbon debate great deal wonderful graph report switching current generation fleet coalfired power station switchoff schedule pretty oneforone mix carbon reduction target fact solved entire carbon debate simple rule coalfired power station existing run existing amortise lifestyle subsidise anything run down generation want long emission market decide easy policy pretty straightforward solved target apparently lot complex mechanism confuse with strength thought report number economy though number large aluminium smelter question future aluminium sector linked power source world competitive nuclear australian world competitive price match international price lowcost electron power aluminium aluminium smelter base power intimately linked talk should audience member undergraduate mechanical engineer university sydney question part completing undergraduate thesis solar thermal power making cheaper investment solar thermal australia proven storage well panel part one part two mechanical undergraduate lot friend lot difficulty finding meaningful job australia bank possibly renewable energy economy brightest overseas mary okane answering bit solar thermal investment acer arena solar flagship reason solar thermal australias dominance space stop roaring ahead australia innovator energy hope overseas stay great energy innovator entrepreneur robyn william david mill university overseas developed solar thermal sold interest here audience member andrew tanner other tony irwin solar thermal nuclear advanced nuclear generation molten salt reactor molten salt thermal match future gary ellem make quick comment molten salt storage great peak shifting technology many cloudy day technology important put context hassle depth winter cloudy day hour worth storage salt bridge gap help there important federally party royally stuffed renewable energy target previously initial target decided dump household solar plan pulling crashed price recently renegotiationif international company put cent trust term longterm government policy consistency decade consistency year audience member jame reynold building large humongous square kilometre size solar farm desert areas north tropic capricorn unsuitable pastoral purpose robyn william space gary ellem reason glut power system built voltage cable connect robyn william satisfied answer gary ellem make wonderful sense term wonderful era power generation sound fantastic make argument turn make economic moment prepared make argument audience member bright sunny day rain cloud gary ellem wonderful mile nowhere build enormously long powerline unsensible large piece infrastructure organise work fund robyn william yes fund perpetual question panel applause talking south wale chief scientist professor mary okane professor ben hankamer university queensland gary ellem university newcastle tony irwin anu professor deo prasad university south wale panel put geological australia production david fisher steven tilley robyn william guest ","m_szGeo1":"Australia","m_szSourceType":"source_news","m_szSrcUrl":"http://www.abc.net.au/radionational/programs/scienceshow/new-document/7104580","m_Places":["Sydney","France","China","Australia","Africa","Europe","United States","Boston","Qu√©bec","Canberra","Well","Estonia","Hazelwood","Uk","Canada","Victoria","New South Wales","Queensland","Melbourne","Japan","Tesla","Denmark","Newcastle","Camden","Southeast Asia","Singapore","Jerusalem","Finland","Sweden","Vienna","Fukushima"],"m_People":["So Synroc","Robyn Williams","Michael Blastland","Anthony Patt","Tony Patt","Tony Irwin","Professor Ben Hankamer","Mary O'kane","Martin Thomas","Deo Prasad","Jack Singh","Ben Hankamer","Tony Manning","John Burgess","Tony Wood","Tony Wheeler","Ziggy Switkowski","David Fisher","Andrew Tanner","James Reynolds","Steven Tilley"],"m_Companies":["Getty Images","Society Of Australia","Sahara","Bbc","Swiss Institute Of Technology","University Of New South Wales","Oecd","Nem","New South Wales Government","Abc","La Trobe University","University Of Queensland","Tom Farrell Institute","University Of Newcastle","Moomba","Real Estate Association Of New South Wales","Iea","International Energy Agency","Grattan Institute","Lifespan","Google","Clinton Administration","Davos","Diesel","Leichardt Council","Csiro","Remind","Bureau Of Statistics","Buffer","Slack","Crc","Target","University Of Sydney","Gap"],"m_BiGrams":["robyn william","gary ellem","south wale","audience member","solar panel","renewable energy","tony irwin","ben hankamer","put solar","michael blastland","deo prasad","mary okane","public transport","solar thermal","fossil fuel","solar power","anthony patt","university south","power station","energy use","megawatt hour","low carbon","production system","energy source","alternative energy","private passenger","capital cost","enormous amount","manufacturing policy","geological australia","generate electricity","lose power","black coal","brown coal","world record","chief scientist","energy technology","martin thomas","science engineering","building city","global energy","fuel solution","university newcastle","rental property","roof space","panel roof","heating cooling","aluminium smelter","residential sector","energy user","nuclear power","coalfired power","molten salt"],"m_TriGrams":["university south wale","solar panel roof","coalfired power station"],"m_SocialTags":[],"m_Topics":[],"m_Industry":[],"m_Technology":[],"m_BiCnt":[20,18,14,13,11,11,8,8,7,7,7,6,6,6,5,5,5,5,5,5,4,4,4,4,4,4,4,4,4,3,3,3,3,3,3,3,3,3,3,3,3,3,3,3,3,3,3,3,3,3,3,3,3],"m_TriCnt":[5,3,3],"m_iDocBodyWordCnt":3810}
